[1,["ecpdLyjvZBwrvm+cedCcQy","e6OwLmxpxGV5kXItDSoTw3","1da30bbc0","1c027e35d","3dWjSFOotCfreszhuL5fvl","7cGHT67QFFn7xQAUz0+rfm","91VlCHfXdD7o4Gn32kun0W","08FGc/moVMQ58axkyapsM1","f4cpunVuZPYqWKT6GBLuW0","b0TjU7PWBEdIINay9Le4iL","51htJ7iuVJlp2iPGJ7SQX0","2akayK/I5DQLreBRdjb6yp","e0lKlrtfpFzIDSWxGlw3SO","87VqqYyX5PnZ5QkqXysabA","eayHiL1w5DtrvgRYRCco3t"],["node","_spriteFrame","_textureSetter","root","data"],["cc.SpriteFrame",["cc.Node",["_name","_groupIndex","_active","_components","_prefab","_parent","_contentSize","_trs","_children","_color"],0,9,4,1,5,7,2,5],["cc.Sprite",["_sizeMode","_type","node","_materials","_spriteFrame"],1,1,3,6],["cc.PrefabInfo",["fileId","root"],2,1],["cc.ClickEvent",["_componentId","handler","customEventData","target"],0,1],["cc.Label",["_string","_fontSize","_lineHeight","_N$horizontalAlign","_N$verticalAlign","_N$overflow","_N$cacheMode","node","_materials"],-4,1,3],["cc.Prefab",["_name"],2],["97e5fXvk8lCg4mXnDhKQB8O",["node"],3,1],["cc.Layout",["_resize","_N$layoutType","_N$spacingX","node","_layoutSize"],0,1,5],["cc.Button",["node","clickEvents"],3,1,9]],[[3,0,1,2],[2,2,3,4,1],[1,0,1,5,3,4,9,6,7,3],[1,0,1,5,3,4,6,7,3],[5,0,1,2,3,4,6,7,8,7],[1,0,1,5,8,3,4,6,7,3],[9,0,1,1],[1,0,2,1,5,3,4,6,7,4],[1,0,2,1,5,3,4,6,4],[4,0,1,2,3,4],[8,0,1,2,3,4,4],[2,1,0,2,3,4,3],[4,0,1,3,3],[6,0,2],[1,0,1,8,3,4,3],[7,0,1],[3,1,1],[2,0,2,3,4,2],[5,0,1,2,3,4,5,7,8,7]],[[[{"name":"HotSell18","rect":[1224,1856,125,185],"offset":[0,0],"originalSize":[125,185],"capInsets":[0,0,0,0]}],[0],0,[0],[2],[2]],[[{"name":"HotSell16","rect":[1060,509,106,60],"offset":[0,0],"originalSize":[106,60],"capInsets":[0,0,0,0]}],[0],0,[0],[2],[2]],[[{"name":"HotSell20","rect":[195,1185,40,48],"offset":[0,0],"originalSize":[40,48],"rotated":1,"capInsets":[0,0,0,0]}],[0],0,[0],[2],[3]],[[{"name":"HotSell13","rect":[3,429,165,52],"offset":[0,0],"originalSize":[165,52],"capInsets":[0,0,0,0]}],[0],0,[0],[2],[3]],[[{"name":"HotSell19","rect":[194,1231,40,48],"offset":[0,0],"originalSize":[40,48],"rotated":1,"capInsets":[0,0,0,0]}],[0],0,[0],[2],[3]],[[{"name":"HotSell15","rect":[849,1763,87,73],"offset":[-2.5,0],"originalSize":[92,73],"rotated":1,"capInsets":[0,0,0,0]}],[0],0,[0],[2],[2]],[[{"name":"HotSell17","rect":[1355,1856,125,185],"offset":[0,0],"originalSize":[125,185],"capInsets":[34,80,91,105]}],[0],0,[0],[2],[2]],[[[13,"UiHotSellChooseEff"],[14,"UiHotSellChooseEff",1,[-3,-4,-5,-6,-7,-8,-9,-10,-11,-12,-13,-14,-15,-16,-17,-18,-19,-20,-21],[[15,-2]],[16,-1]],[5,"Node",1,1,[-23,-24,-25,-26,-27,-28,-29,-30,-31,-32,-33,-34,-35,-36,-37,-38,-39,-40,-41,-42],[[10,1,1,5,-22,[5,495,5]]],[0,"ecmi4MXtdHmZxWxj/+aVIx",1],[5,495,5],[0,103.674,0,0,0,0,1,1,1,1]],[5,"Node",1,1,[-44,-45,-46,-47,-48,-49,-50,-51,-52,-53,-54,-55,-56,-57,-58,-59,-60,-61,-62,-63],[[10,1,1,5,-43,[5,495,5]]],[0,"c8VGKbIPNFf58c2lYFcF5T",1],[5,495,5],[0,-139.101,0,0,0,0,1,1,1,1]],[5,"Node1",1,1,[-66,-67,-68,-69],[[1,-64,[53],54],[6,-65,[[9,"97e5fXvk8lCg4mXnDhKQB8O","btnItemClick","0",1]]]],[0,"6bschEEQxAZKSpPooN7Ehy",1],[5,125,185],[-182.441,-29.924,0,0,0,0,1,1,1,1]],[5,"Node2",1,1,[-72,-73,-74,-75],[[17,0,-70,[63],64],[6,-71,[[9,"97e5fXvk8lCg4mXnDhKQB8O","btnItemClick","1",1]]]],[0,"e3QXMz7j5EEokBFo5RALLc",1],[5,180,185],[-1.436,-29.924,0,0,0,0,1,1,1,1]],[5,"Node3",1,1,[-78,-79,-80,-81],[[1,-76,[73],74],[6,-77,[[9,"97e5fXvk8lCg4mXnDhKQB8O","btnItemClick","2",1]]]],[0,"2bjsXcBYxCEpGU9UIL2IB8",1],[5,125,185],[183.878,-29.924,0,0,0,0,1,1,1,1]],[5,"BtnAll",1,1,[-84],[[1,-82,[119],120],[6,-83,[[12,"97e5fXvk8lCg4mXnDhKQB8O","btnWatchVideo",1]]]],[0,"dfkCjruTVL1Z6o3lvCJ5De",1],[5,178,65],[123.543,-198,0,0,0,0,1,1,1,1]],[3,"BtnConfirm",1,1,[[1,-85,[115],116],[6,-86,[[12,"97e5fXvk8lCg4mXnDhKQB8O","btnConfirm",1]]]],[0,"da6mvLXj1IWJHC7koJ8kJZ",1],[5,178,65],[-146.527,-198,0,0,0,0,1,1,1,1]],[3,"HotSell1",1,1,[[11,1,0,-87,[0],1]],[0,"73IsW5ohVEC7by03kOUUp6",1],[5,656,639],[0,41.151,0,0,0,0,1,1,1,1]],[3,"HotSell13",1,1,[[1,-88,[2],3]],[0,"30PiXiEORN/qsS/OgBhn6b",1],[5,165,52],[-40,279.151,0,0,0,0,1,1,1,1]],[2,"TxtDes",1,1,[[18,"选择您需要开启的功能（3选2）",30,35,1,1,2,-89,[4]]],[0,"43PyQWFnRKfqt8b52z4BYJ",1],[4,4287794323],[5,330,80],[0,157.557,0,0,0,0,1,1,1,1]],[2,"BasketInfo9",1,2,[[1,-90,[5],6]],[0,"c3gDQ1txhDU7xDOJ84iPD5",1],[4,4289111719],[5,20,5],[-237.5,0,0,0,0,0,1,1,1,1]],[2,"BasketInfo9",1,2,[[1,-91,[7],8]],[0,"78QyXJe0xK6q1/BZnWdal/",1],[4,4289111719],[5,20,5],[-212.5,0,0,0,0,0,1,1,1,1]],[2,"BasketInfo9",1,2,[[1,-92,[9],10]],[0,"b6y4cqSpZKlJjvRfvY9Oxq",1],[4,4289111719],[5,20,5],[-187.5,0,0,0,0,0,1,1,1,1]],[2,"BasketInfo9",1,2,[[1,-93,[11],12]],[0,"05uVHTp5NKbrIL7D6gfdfe",1],[4,4289111719],[5,20,5],[-162.5,0,0,0,0,0,1,1,1,1]],[2,"BasketInfo9",1,2,[[1,-94,[13],14]],[0,"a6ZTKNPgFP1b5QE+BDRJmT",1],[4,4289111719],[5,20,5],[-137.5,0,0,0,0,0,1,1,1,1]],[2,"BasketInfo9",1,2,[[1,-95,[15],16]],[0,"eckTwydv9P65x1uymgADyu",1],[4,4289111719],[5,20,5],[-112.5,0,0,0,0,0,1,1,1,1]],[2,"BasketInfo9",1,2,[[1,-96,[17],18]],[0,"9dE/XuDotJsYzN84uEbOG0",1],[4,4289111719],[5,20,5],[-87.5,0,0,0,0,0,1,1,1,1]],[2,"BasketInfo9",1,2,[[1,-97,[19],20]],[0,"e71J2RAgxBk5X2tFsSj8TI",1],[4,4289111719],[5,20,5],[-62.5,0,0,0,0,0,1,1,1,1]],[2,"BasketInfo9",1,2,[[1,-98,[21],22]],[0,"22bi+FeLxHELrihjxMNv7o",1],[4,4289111719],[5,20,5],[-37.5,0,0,0,0,0,1,1,1,1]],[2,"BasketInfo9",1,2,[[1,-99,[23],24]],[0,"8aad6s00BOIo2tEL3HEBRL",1],[4,4289111719],[5,20,5],[-12.5,0,0,0,0,0,1,1,1,1]],[2,"BasketInfo9",1,2,[[1,-100,[25],26]],[0,"cfW/VROx1EZ6pyDxfOd38P",1],[4,4289111719],[5,20,5],[12.5,0,0,0,0,0,1,1,1,1]],[2,"BasketInfo9",1,2,[[1,-101,[27],28]],[0,"deVL1zMdhMGZfpLzyocmfq",1],[4,4289111719],[5,20,5],[37.5,0,0,0,0,0,1,1,1,1]],[2,"BasketInfo9",1,2,[[1,-102,[29],30]],[0,"01oIeSc/hIp6EI4211lSiq",1],[4,4289111719],[5,20,5],[62.5,0,0,0,0,0,1,1,1,1]],[2,"BasketInfo9",1,2,[[1,-103,[31],32]],[0,"18RE9ua8pEQo2ZdcXC/Qax",1],[4,4289111719],[5,20,5],[87.5,0,0,0,0,0,1,1,1,1]],[2,"BasketInfo9",1,2,[[1,-104,[33],34]],[0,"1dgG5+8IRHLp9E+Or1UFgL",1],[4,4289111719],[5,20,5],[112.5,0,0,0,0,0,1,1,1,1]],[2,"BasketInfo9",1,2,[[1,-105,[35],36]],[0,"a8TuUcDP9F5Je5F0fYJvdQ",1],[4,4289111719],[5,20,5],[137.5,0,0,0,0,0,1,1,1,1]],[2,"BasketInfo9",1,2,[[1,-106,[37],38]],[0,"04bjuXEPRLYpLLr+Hy48La",1],[4,4289111719],[5,20,5],[162.5,0,0,0,0,0,1,1,1,1]],[2,"BasketInfo9",1,2,[[1,-107,[39],40]],[0,"78xBkPO39GfqBS/yKo+G5e",1],[4,4289111719],[5,20,5],[187.5,0,0,0,0,0,1,1,1,1]],[2,"BasketInfo9",1,2,[[1,-108,[41],42]],[0,"70LDuqSr5KbLWy/J8WigFH",1],[4,4289111719],[5,20,5],[212.5,0,0,0,0,0,1,1,1,1]],[2,"BasketInfo9",1,2,[[1,-109,[43],44]],[0,"0fYafpm/hIWI9pjuctRfY+",1],[4,4289111719],[5,20,5],[237.5,0,0,0,0,0,1,1,1,1]],[3,"SprIcon",1,4,[[1,-110,[45],46]],[0,"87UafO+EFPAr66maIXjlY2",1],[5,106,60],[5.746,11.492,0,0,0,0,1,1,1,1]],[3,"SprArrowGrey",1,4,[[1,-111,[47],48]],[0,"64y+vYqvJAQJk19QAR5udG",1],[5,40,48],[-41.66,-67.519,0,0,0,0,1,1,1,1]],[7,"SprArrow",false,1,4,[[1,-112,[49],50]],[0,"21+9mH6ApJlLixYN/TmDYd",1],[5,40,48],[-41.66,-67.519,0,0,0,0,1,1,1,1]],[8,"SprOutLine",false,1,4,[[1,-113,[51],52]],[0,"faB6oIf8tOjoYlmme3SpSq",1],[5,125,185]],[3,"SprIcon",1,5,[[1,-114,[55],56]],[0,"60z4DZGAlB1LHzg3DE3CD6",1],[5,101,63],[-1.437,12.928,0,0,0,0,1,1,1,1]],[3,"SprArrowGrey",1,5,[[1,-115,[57],58]],[0,"f5BXHfvXFPE69UCxcgYitG",1],[5,40,48],[-68.955,-67.519,0,0,0,0,1,1,1,1]],[7,"SprArrow",false,1,5,[[1,-116,[59],60]],[0,"63Yb0NQvRI0KsjDFnj9+dq",1],[5,40,48],[-68.955,-67.519,0,0,0,0,1,1,1,1]],[8,"SprOutLine",false,1,5,[[11,1,0,-117,[61],62]],[0,"87HJ3222dFPIOB+ocpZGf6",1],[5,178,183]],[3,"SprIcon",1,6,[[1,-118,[65],66]],[0,"fb4GQTOQxJvYDqMljIbYJT",1],[5,87,73],[2.873,11.492,0,0,0,0,1,1,1,1]],[3,"SprArrowGrey",1,6,[[1,-119,[67],68]],[0,"a1+/ruvyhDW6cATVDWsmfj",1],[5,40,48],[-40.224,-67.519,0,0,0,0,1,1,1,1]],[7,"SprArrow",false,1,6,[[1,-120,[69],70]],[0,"5chNuANaRIjqDQgsTLjqer",1],[5,40,48],[-40.224,-67.518,0,0,0,0,1,1,1,1]],[8,"SprOutLine",false,1,6,[[1,-121,[71],72]],[0,"97zdjE+5ZDW54Nbbun6k4S",1],[5,125,185]],[2,"BasketInfo9",1,3,[[1,-122,[75],76]],[0,"69ezciQKtGOIS/Ptsa9MWb",1],[4,4289111719],[5,20,5],[-237.5,0,0,0,0,0,1,1,1,1]],[2,"BasketInfo9",1,3,[[1,-123,[77],78]],[0,"8fDc6LW0NLxIUb6w1yy9Pg",1],[4,4289111719],[5,20,5],[-212.5,0,0,0,0,0,1,1,1,1]],[2,"BasketInfo9",1,3,[[1,-124,[79],80]],[0,"0dgT5aOcRKGKtbvDueRvlh",1],[4,4289111719],[5,20,5],[-187.5,0,0,0,0,0,1,1,1,1]],[2,"BasketInfo9",1,3,[[1,-125,[81],82]],[0,"0aWajxtztAoYA/G5ULtoNM",1],[4,4289111719],[5,20,5],[-162.5,0,0,0,0,0,1,1,1,1]],[2,"BasketInfo9",1,3,[[1,-126,[83],84]],[0,"03NldnDDlOYqfTlgGJ0D3d",1],[4,4289111719],[5,20,5],[-137.5,0,0,0,0,0,1,1,1,1]],[2,"BasketInfo9",1,3,[[1,-127,[85],86]],[0,"620c6iXTpAfKOKHyJaj7LT",1],[4,4289111719],[5,20,5],[-112.5,0,0,0,0,0,1,1,1,1]],[2,"BasketInfo9",1,3,[[1,-128,[87],88]],[0,"e3zwKcTOlLTKb8k5Vu9h6D",1],[4,4289111719],[5,20,5],[-87.5,0,0,0,0,0,1,1,1,1]],[2,"BasketInfo9",1,3,[[1,-129,[89],90]],[0,"19uFLsFllHwbaQE6X8u+f1",1],[4,4289111719],[5,20,5],[-62.5,0,0,0,0,0,1,1,1,1]],[2,"BasketInfo9",1,3,[[1,-130,[91],92]],[0,"5cn7R/qP9JdK/kf8ZD/vGy",1],[4,4289111719],[5,20,5],[-37.5,0,0,0,0,0,1,1,1,1]],[2,"BasketInfo9",1,3,[[1,-131,[93],94]],[0,"d1XRWoA1RI1LX94sSZ8mZV",1],[4,4289111719],[5,20,5],[-12.5,0,0,0,0,0,1,1,1,1]],[2,"BasketInfo9",1,3,[[1,-132,[95],96]],[0,"34tzQZa4NLGZvGDWFQb7nG",1],[4,4289111719],[5,20,5],[12.5,0,0,0,0,0,1,1,1,1]],[2,"BasketInfo9",1,3,[[1,-133,[97],98]],[0,"0cqTXNsmVJm5bOcxZslhAu",1],[4,4289111719],[5,20,5],[37.5,0,0,0,0,0,1,1,1,1]],[2,"BasketInfo9",1,3,[[1,-134,[99],100]],[0,"e0iSSdi2RPdZ3aqSZZTqdO",1],[4,4289111719],[5,20,5],[62.5,0,0,0,0,0,1,1,1,1]],[2,"BasketInfo9",1,3,[[1,-135,[101],102]],[0,"d38IzrTsFIGpL6DQkkUx/Z",1],[4,4289111719],[5,20,5],[87.5,0,0,0,0,0,1,1,1,1]],[2,"BasketInfo9",1,3,[[1,-136,[103],104]],[0,"83klA/bd1NWo2nvTshUV+h",1],[4,4289111719],[5,20,5],[112.5,0,0,0,0,0,1,1,1,1]],[2,"BasketInfo9",1,3,[[1,-137,[105],106]],[0,"07D5kXZW9Chbs0gvoH1b+5",1],[4,4289111719],[5,20,5],[137.5,0,0,0,0,0,1,1,1,1]],[2,"BasketInfo9",1,3,[[1,-138,[107],108]],[0,"f7aqFqzddNzLxVAnJpW5dc",1],[4,4289111719],[5,20,5],[162.5,0,0,0,0,0,1,1,1,1]],[2,"BasketInfo9",1,3,[[1,-139,[109],110]],[0,"7auTuNbY1BgLjiDoMB37Kq",1],[4,4289111719],[5,20,5],[187.5,0,0,0,0,0,1,1,1,1]],[2,"BasketInfo9",1,3,[[1,-140,[111],112]],[0,"98bj9/Ld5Kk7lPGq37L4bd",1],[4,4289111719],[5,20,5],[212.5,0,0,0,0,0,1,1,1,1]],[2,"BasketInfo9",1,3,[[1,-141,[113],114]],[0,"62DTQg3E1FEKb3qNlD+MWA",1],[4,4289111719],[5,20,5],[237.5,0,0,0,0,0,1,1,1,1]],[3,"BtnBG4",1,7,[[1,-142,[117],118]],[0,"b3lFQJMgFFIo36dpMKlR/1",1],[5,88,73],[-96.249,1.437,0,0,0,0,1,1,1,1]],[2,"TxtTrade",1,1,[[4,"自动招待",25,25,1,1,2,-143,[121]]],[0,"4aBnoyIjFDRrnw6x7exaIg",1],[4,4284108124],[5,100,25],[-183.836,46.213,0,0,0,0,1,1,1,1]],[2,"TxtVisitor",1,1,[[4,"来客速度翻倍",25,25,1,1,2,-144,[122]]],[0,"62osu0pM5AfrUFnfpzyEFt",1],[4,4284108124],[5,150,25],[1.478,46.213,0,0,0,0,1,1,1,1]],[2,"TxtProfit",1,1,[[4,"利润翻倍",25,25,1,1,2,-145,[123]]],[0,"b5HsZytNNLUpiDynTSAtM0",1],[4,4284108124],[5,100,25],[185.355,46.213,0,0,0,0,1,1,1,1]],[2,"TxtConfirm",1,1,[[4,"确定",30,30,1,1,2,-146,[124]]],[0,"38O1qukYFDSKpKnPSpNaoE",1],[4,4284108124],[5,60,30],[-142.177,-199.436,0,0,0,0,1,1,1,1]],[2,"TxtAll",1,1,[[4,"全都要",30,30,1,1,2,-147,[125]]],[0,"2dd1dsIHxDtIWnaI/wgd/H",1],[4,4284108124],[5,90,30],[137.949,-199.436,0,0,0,0,1,1,1,1]],[2,"TxtProfit",1,1,[[4,"确定",30,30,1,1,2,-148,[126]]],[0,"a8Qd/GA+BAoJdLapOAbHT7",1],[4,4284108124],[5,60,30],[-142.177,-199.436,0,0,0,0,1,1,1,1]],[2,"TxtTimesDes",1,1,[[4,"X2",30,30,1,1,2,-149,[127]]],[0,"5cY96L9sZCEJy0vKRZIeOy",1],[4,4284108124],[5,36.69,30],[-181.51,-106.812,0,0,0,0,1,1,1,1]],[2,"TxtTimesDes",1,1,[[4,"X2",30,30,1,1,2,-150,[128]]],[0,"4b8bBMDj9PZq8A3GT8eVTH",1],[4,4284108124],[5,36.69,30],[-29.252,-106.812,0,0,0,0,1,1,1,1]],[2,"TxtTimesDes",1,1,[[4,"X2",30,30,1,1,2,-151,[129]]],[0,"79E+1PG9ZD85BFa1XMlVIt",1],[4,4284108124],[5,36.69,30],[185.178,-106.812,0,0,0,0,1,1,1,1]]],0,[0,3,1,0,0,1,0,-1,9,0,-2,10,0,-3,11,0,-4,2,0,-5,4,0,-6,5,0,-7,6,0,-8,3,0,-9,8,0,-10,7,0,-11,65,0,-12,66,0,-13,67,0,-14,68,0,-15,69,0,-16,70,0,-17,71,0,-18,72,0,-19,73,0,0,2,0,-1,12,0,-2,13,0,-3,14,0,-4,15,0,-5,16,0,-6,17,0,-7,18,0,-8,19,0,-9,20,0,-10,21,0,-11,22,0,-12,23,0,-13,24,0,-14,25,0,-15,26,0,-16,27,0,-17,28,0,-18,29,0,-19,30,0,-20,31,0,0,3,0,-1,44,0,-2,45,0,-3,46,0,-4,47,0,-5,48,0,-6,49,0,-7,50,0,-8,51,0,-9,52,0,-10,53,0,-11,54,0,-12,55,0,-13,56,0,-14,57,0,-15,58,0,-16,59,0,-17,60,0,-18,61,0,-19,62,0,-20,63,0,0,4,0,0,4,0,-1,32,0,-2,33,0,-3,34,0,-4,35,0,0,5,0,0,5,0,-1,36,0,-2,37,0,-3,38,0,-4,39,0,0,6,0,0,6,0,-1,40,0,-2,41,0,-3,42,0,-4,43,0,0,7,0,0,7,0,-1,64,0,0,8,0,0,8,0,0,9,0,0,10,0,0,11,0,0,12,0,0,13,0,0,14,0,0,15,0,0,16,0,0,17,0,0,18,0,0,19,0,0,20,0,0,21,0,0,22,0,0,23,0,0,24,0,0,25,0,0,26,0,0,27,0,0,28,0,0,29,0,0,30,0,0,31,0,0,32,0,0,33,0,0,34,0,0,35,0,0,36,0,0,37,0,0,38,0,0,39,0,0,40,0,0,41,0,0,42,0,0,43,0,0,44,0,0,45,0,0,46,0,0,47,0,0,48,0,0,49,0,0,50,0,0,51,0,0,52,0,0,53,0,0,54,0,0,55,0,0,56,0,0,57,0,0,58,0,0,59,0,0,60,0,0,61,0,0,62,0,0,63,0,0,64,0,0,65,0,0,66,0,0,67,0,0,68,0,0,69,0,0,70,0,0,71,0,0,72,0,0,73,0,4,1,151],[0,0,0,0,0,0,0,0,0,0,0,0,0,0,0,0,0,0,0,0,0,0,0,0,0,0,0,0,0,0,0,0,0,0,0,0,0,0,0,0,0,0,0,0,0,0,0,0,0,0,0,0,0,0,0,0,0,0,0,0,0,0,0,0,0,0,0,0,0,0,0,0,0,0,0,0,0,0,0,0,0,0,0,0,0,0,0,0,0,0,0,0,0,0,0,0,0,0,0,0,0,0,0,0,0,0,0,0,0,0,0,0,0,0,0,0,0,0,0,0,0,0,0,0,0,0,0,0,0,0],[-1,1,-1,1,-1,-1,1,-1,1,-1,1,-1,1,-1,1,-1,1,-1,1,-1,1,-1,1,-1,1,-1,1,-1,1,-1,1,-1,1,-1,1,-1,1,-1,1,-1,1,-1,1,-1,1,-1,1,-1,1,-1,1,-1,1,-1,1,-1,1,-1,1,-1,1,-1,1,-1,1,-1,1,-1,1,-1,1,-1,1,-1,1,-1,1,-1,1,-1,1,-1,1,-1,1,-1,1,-1,1,-1,1,-1,1,-1,1,-1,1,-1,1,-1,1,-1,1,-1,1,-1,1,-1,1,-1,1,-1,1,-1,1,-1,1,-1,1,-1,1,-1,-1,-1,-1,-1,-1,-1,-1,-1],[0,9,0,10,0,0,1,0,1,0,1,0,1,0,1,0,1,0,1,0,1,0,1,0,1,0,1,0,1,0,1,0,1,0,1,0,1,0,1,0,1,0,1,0,1,0,11,0,4,0,5,0,6,0,7,0,12,0,4,0,5,0,6,0,7,0,13,0,4,0,5,0,6,0,7,0,1,0,1,0,1,0,1,0,1,0,1,0,1,0,1,0,1,0,1,0,1,0,1,0,1,0,1,0,1,0,1,0,1,0,1,0,1,0,1,0,8,0,14,0,8,0,0,0,0,0,0,0,0,0]],[[{"name":"HotSell14","rect":[110,962,101,63],"offset":[0,0],"originalSize":[101,63],"capInsets":[0,0,0,0]}],[0],0,[0],[2],[3]]]]